aws_encryption_sdk/__init__.py
aws_encryption_sdk/compatability.py
aws_encryption_sdk/exceptions.py
aws_encryption_sdk/identifiers.py
aws_encryption_sdk/streaming_client.py
aws_encryption_sdk/structures.py
aws_encryption_sdk/caches/__init__.py
aws_encryption_sdk/caches/base.py
aws_encryption_sdk/caches/local.py
aws_encryption_sdk/caches/null.py
aws_encryption_sdk/internal/__init__.py
aws_encryption_sdk/internal/arn.py
aws_encryption_sdk/internal/defaults.py
aws_encryption_sdk/internal/deprecation.py
aws_encryption_sdk/internal/str_ops.py
aws_encryption_sdk/internal/structures.py
aws_encryption_sdk/internal/crypto/__init__.py
aws_encryption_sdk/internal/crypto/authentication.py
aws_encryption_sdk/internal/crypto/data_keys.py
aws_encryption_sdk/internal/crypto/elliptic_curve.py
aws_encryption_sdk/internal/crypto/encryption.py
aws_encryption_sdk/internal/crypto/iv.py
aws_encryption_sdk/internal/crypto/wrapping_keys.py
aws_encryption_sdk/internal/formatting/__init__.py
aws_encryption_sdk/internal/formatting/deserialize.py
aws_encryption_sdk/internal/formatting/encryption_context.py
aws_encryption_sdk/internal/formatting/serialize.py
aws_encryption_sdk/internal/utils/__init__.py
aws_encryption_sdk/internal/utils/commitment.py
aws_encryption_sdk/internal/utils/signature.py
aws_encryption_sdk/internal/utils/streams.py
aws_encryption_sdk/key_providers/__init__.py
aws_encryption_sdk/key_providers/base.py
aws_encryption_sdk/key_providers/kms.py
aws_encryption_sdk/key_providers/raw.py
aws_encryption_sdk/materials_managers/__init__.py
aws_encryption_sdk/materials_managers/base.py
aws_encryption_sdk/materials_managers/caching.py
aws_encryption_sdk/materials_managers/default.py
aws_encryption_sdk/materials_managers/mpl/__init__.py
aws_encryption_sdk/materials_managers/mpl/cmm.py
aws_encryption_sdk/materials_managers/mpl/materials.py
aws_encryption_sdk-4.0.3.dist-info/LICENSE
aws_encryption_sdk-4.0.3.dist-info/METADATA
aws_encryption_sdk-4.0.3.dist-info/WHEEL
aws_encryption_sdk-4.0.3.dist-info/top_level.txt
aws_encryption_sdk-4.0.3.dist-info/RECORD
