Metadata-Version: 2.1
Name: aws-encryption-sdk
Version: 4.0.3
Summary: AWS Encryption SDK implementation for Python
Home-page: https://github.com/aws/aws-encryption-sdk-python
Author: Amazon Web Services
Author-email: aws-cryptools@amazon.com
Maintainer: Amazon Web Services
License: Apache License 2.0
Keywords: aws-encryption-sdk aws kms encryption
Classifier: Development Status :: 5 - Production/Stable
Classifier: Intended Audience :: Developers
Classifier: Natural Language :: English
Classifier: License :: OSI Approved :: Apache Software License
Classifier: Programming Language :: Python
Classifier: Programming Language :: Python :: 3
Classifier: Programming Language :: Python :: 3.8
Classifier: Programming Language :: Python :: 3.9
Classifier: Programming Language :: Python :: 3.10
Classifier: Programming Language :: Python :: 3.11
Classifier: Programming Language :: Python :: 3.12
Classifier: Programming Language :: Python :: Implementation :: CPython
Classifier: Topic :: Security
Classifier: Topic :: Security :: Cryptography
License-File: LICENSE
Requires-Dist: boto3>=1.10.0
Requires-Dist: cryptography>=3.4.6
Requires-Dist: attrs>=17.4.0
Requires-Dist: wrapt>=1.10.11
Provides-Extra: mpl
Requires-Dist: aws-cryptographic-material-providers<=1.11.1,>=1.7.4; extra == "mpl"
